certbot_dns_regru-1.1.1.dist-info/licenses/LICENSE.txt
certbot_regru/__init__.py
certbot_regru/dns.py
certbot_regru/dns_test_real.py
etc/letsencrypt/regru.ini
certbot_dns_regru-1.1.1.dist-info/METADATA
certbot_dns_regru-1.1.1.dist-info/WHEEL
certbot_dns_regru-1.1.1.dist-info/entry_points.txt
certbot_dns_regru-1.1.1.dist-info/top_level.txt
certbot_dns_regru-1.1.1.dist-info/RECORD
