Metadata-Version: 2.4
Name: certbot-dns-regru
Version: 1.1.1
Summary: Reg.ru DNS authenticator plugin for Certbot
Author-email: Percifal <percifal@shpw.ru>
License-Expression: MIT
Project-URL: Homepage, https://github.com/shadowpercifal/certbot-dns-regru
Classifier: Development Status :: 5 - Production/Stable
Classifier: Environment :: Plugins
Classifier: Intended Audience :: System Administrators
Classifier: Operating System :: POSIX :: Linux
Classifier: Programming Language :: Python
Classifier: Programming Language :: Python :: 3
Classifier: Programming Language :: Python :: 3.4
Classifier: Programming Language :: Python :: 3.5
Classifier: Programming Language :: Python :: 3.6
Classifier: Programming Language :: Python :: 3.7
Classifier: Programming Language :: Python :: 3.8
Classifier: Programming Language :: Python :: 3.9
Classifier: Programming Language :: Python :: 3.10
Classifier: Topic :: Internet :: WWW/HTTP
Classifier: Topic :: Security
Classifier: Topic :: System :: Installation/Setup
Classifier: Topic :: System :: Networking
Classifier: Topic :: System :: Systems Administration
Classifier: Topic :: Utilities
Requires-Python: >=3.4
License-File: LICENSE.txt
Requires-Dist: acme>=0.21.1
Requires-Dist: certbot>=0.21.1
Requires-Dist: requests>=2.9.1
Requires-Dist: setuptools
Requires-Dist: zope.interface
Dynamic: license-file
